.editorconfig
.gitignore
LICENSE
MANIFEST.in
README.md
mkdocs.yml
requirements.txt
requirements_dev.txt
setup.cfg
setup.py
.github/ISSUE_TEMPLATE/bug_report.md
.github/ISSUE_TEMPLATE/config.yml
.github/ISSUE_TEMPLATE/feature_request.md
.github/workflows/build.yml
.github/workflows/docs.yml
.github/workflows/pypi.yml
docs/changelog.md
docs/contributing.md
docs/faq.md
docs/geosdemopyff.md
docs/index.md
docs/installation.md
docs/usage.md
docs/overrides/main.html
geosdemopyff/__init__.py
geosdemopyff/geosdemopyff.py
geosdemopyff.egg-info/PKG-INFO
geosdemopyff.egg-info/SOURCES.txt
geosdemopyff.egg-info/dependency_links.txt
geosdemopyff.egg-info/not-zip-safe
geosdemopyff.egg-info/top_level.txt
tests/__init__.py
tests/test_geosdemopyff.py